mrs_denoising/__init__.py
mrs_denoising/denoising.py
mrs_denoising/mrsi_denoise.py
mrs_denoising/utils.py
mrs_denoising_tools-0.0.2.dist-info/LICENSE
mrs_denoising_tools-0.0.2.dist-info/METADATA
mrs_denoising_tools-0.0.2.dist-info/WHEEL
mrs_denoising_tools-0.0.2.dist-info/entry_points.txt
mrs_denoising_tools-0.0.2.dist-info/top_level.txt
mrs_denoising_tools-0.0.2.dist-info/RECORD
