Metadata-Version: 2.1
Name: mrs-denoising-tools
Version: 0.0.2
Summary: Package for low-rank denoising of magnetic resonance spectroscopic imaging
Home-page: https://git.fmrib.ox.ac.uk/wclarke/low-rank-denoising-tools
Author: Will Clarke
Author-email: william.clarke@ndcn.ox.ac.uk
License: UNKNOWN
Platform: UNKNOWN
Classifier: License :: OSI Approved :: BSD License
Classifier: Operating System :: OS Independent
Classifier: Programming Language :: Python :: 3
Classifier: Programming Language :: Python :: 3 :: Only
Classifier: Programming Language :: Python :: 3.7
Classifier: Programming Language :: Python :: 3.8
Requires-Python: >=3.7
Requires-Dist: numpy
Requires-Dist: nibabel
